sendwave/pants_node/__init__.py
sendwave/pants_node/package.py
sendwave/pants_node/register.py
sendwave/pants_node/subsystems.py
sendwave/pants_node/target.py
sendwave_pants_node-1.2.3.dist-info/METADATA
sendwave_pants_node-1.2.3.dist-info/WHEEL
sendwave_pants_node-1.2.3.dist-info/namespace_packages.txt
sendwave_pants_node-1.2.3.dist-info/top_level.txt
sendwave_pants_node-1.2.3.dist-info/RECORD
